Workbook

Sheet Read Me
A1: Agentic AI in Logistics Operations: Supplementary Review Dataset
A3: Purpose | B3: Reviewer-facing dataset supporting the systematic literature review and its study-level taxonomies.
A4: Corpus | B4: 37 primary studies (S01–S37) retained from 23,116 records retrieved through the consolidated search and selection process.
A5: Observation window | B5: January 2016 through 15 October 2026. No eligible study published before 2024 was retained.
A6: Coding principle | B6: Logistics operations, paradigms, architectures, and capabilities are multi-label dimensions. Primary operation, primary paradigm, dominant topology, confirmed autonomy, and evidence maturity use one final classification per study.
A7: Capabilities | B7: Only capabilities confirmed during full-text reading are counted as demonstrated. S06 is conceptual and therefore has no demonstrated capability-family assignment.
A8: Autonomy | B8: Levels represent demonstrated decision authority: L3 decision support; L4 supervised execution; L5 conditional autonomy; L6 full operational autonomy.
A9: Evidence maturity | B9: EM1 prototype/PoC; EM2 controlled experiment, simulation, benchmark, or synthetic data; EM3 real/historical data; EM4 real-world pilot or case study; EM5 operational deployment.
A10: Quality score | B10: QA1–QA12 are scored 1 (yes), 0.5 (partial), 0 (no), or N/A. Quality score = sum of applicable scores / number of applicable criteria × 100.
A11: Quality classes | B11: Low: <40%; Moderate: 40%–69.9%; High: ≥70%. Methodological quality and evidence maturity are distinct constructs.
A12: Source identifiers | B12: Study IDs S01–S37 match the manuscript tables and figures. Internal record identifiers are retained solely for traceability to the source-level screening logs.
A13: Files not redistributed | B13: Full texts are not included because they remain subject to publisher copyright and access conditions. DOI/URL metadata are provided in the Primary Studies sheet.
A14: Version note | B14: This public workbook contains the final classifications for the 37-study corpus and omits internal working notes, preliminary suggestions, and superseded counts.

Sheet Selection Flow
A1: Stage | B1: Records entering | C1: Records excluded | D1: Records remaining | E1: Criterion or action | F1: Evidence source
A2: Initial search — nine bibliographic sources | D2: 23116 | E2: Complete search string adapted only to source syntax | F2: Consolidated search log
A3: Preliminary filtering | B3: 23116 | C3: 1879 | D3: 21237 | E3: Date, document type, language, venue, retraction, and metadata checks | F3: Pipeline records
A4: Title screening | B4: 21237 | C4: 18934 | D4: 2303 | E4: Fixed title-screening instructions based on the eligibility criteria | F4: Pipeline records
A5: Post-title integrity and document-form check | B5: 2303 | C5: 16 | D5: 2287 | E5: Document integrity, publication status, and form checks | F5: Pipeline records
A6: Abstract screening | B6: 2287 | C6: 854 | D6: 1433 | E6: Fixed abstract-screening instructions based on the eligibility criteria | F6: Pipeline records
A7: Combination and deduplication | B7: 1433 | C7: 427 | D7: 1006 | E7: Normalized DOI, title, authorship, and publication metadata | F7: Pipeline records
A8: Manual recall check | B8: 1006 | D8: 1013 | E8: Three heuristic candidate lists; seven records restored | F8: Manual recall-check log
A9: Short-document assessment | B9: 1013 | C9: 11 | D9: 1002 | E9: EC2 — insufficient research content | F9: Consolidated review log
A10: Extended-abstract eligibility assessment | B10: 1002 | C10: 292 | D10: 710 | E10: EC3–EC6 applied to the available abstract information | F10: Consolidated review log
A11: Substantive agentic-component assessment | B11: 710 | C11: 365 | D11: 345 | E11: EC5/EC12 — substantive agency | F11: Consolidated review log
A12: Software- and operations-level contribution assessment | B12: 345 | C12: 175 | D12: 170 | E12: EC11/EC12 — operational and transferable contribution | F12: Consolidated review log
A13: Manual Three-Pass reading | B13: 170 | C13: 19 | D13: 151 | E13: EC12 — no transferable agentic contribution | F13: Manual review log
A14: Full-text eligibility assessment | B14: 151 | C14: 62 | D14: 89 | E14: Complete eligibility criteria applied through manual full-text reading | F14: Full-text coding records
A15: Modern agentic-capability gate | B15: 89 | C15: 50 | D15: 39 | E15: At least one modern agentic capability in the system core | F15: Full-text coding records
A16: Final agentic-paradigm confirmation | B16: 39 | C16: 2 | D16: 37 | E16: Substantive agentic paradigm confirmed through full-text reading | F16: Full-text coding records
A17: FINAL PRIMARY-STUDY CORPUS | D17: 37 | E17: All eligibility criteria satisfied | F17: Primary-study dataset

Sheet Primary Studies
A1: Study ID | B1: Year | C1: Title | D1: Retained source | E1: Publication venue | F1: DOI or URL | G1: Primary logistics-operation family | H1: Primary operation | I1: Primary agentic paradigm | J1: Dominant architectural topology | K1: Confirmed autonomy | L1: Evidence maturity | M1: Quality score (%) | N1: Quality class | O1: Selection status
A2: S01 | B2: 2026 | C2: Operationalizing Generative and Agentic AI Across Complex Logistics Networks: Architecture, Governance, and Trust Models | D2: ieee_xplore | E2: 2026 ASU International Conference in Emerging Technologies for Sustainability and Intelligent Systems (ICETSIS) | F2: https://ieeexplore.ieee.org/document/11549394/ | G2: Planning, sourcing, and network design | H2: Supply chain planning | I2: Mixed intelligent-agent system | J2: Hybrid distributed and governed | K2: L5 — Conditional autonomy | L2: EM2 — Experimental (simulation / benchmark / synthetic data) | M2: 54.166667 | N2: Moderate | O2: Included after full-text eligibility assessment
A3: S02 | B3: 2026 | C3: RMAS: Risk Mitigation Agent System, An Autonomous Framework for Real-Time Supply Chain Risk Management | D3: ieee_xplore | E3: IEEE Engineering Management Review | F3: https://ieeexplore.ieee.org/document/11538978/ | G3: Planning, sourcing, and network design | H3: Supply chain risk management | I3: LLM-centered agent system | J3: Hierarchical or orchestrated | K3: L5 — Conditional autonomy | L3: EM2 — Experimental (simulation / benchmark / synthetic data) | M3: 95.833333 | N3: High | O3: Included after full-text eligibility assessment
A4: S03 | B4: 2026 | C4: Embodied Intelligent Agents for Adaptive Logistics Scheduling in Power Equipment Supply Networks | D4: ieee_xplore | E4: 2026 2nd International Symposium on AI-Driven Engineering Systems (ISADES) | F4: https://ieeexplore.ieee.org/document/11608150/ | G4: Planning, sourcing, and network design | H4: Supply chain planning | I4: Hybrid LLM and symbolic or analytical system | J4: Hierarchical or orchestrated | K4: L6 — Full operational autonomy | L4: EM2 — Experimental (simulation / benchmark / synthetic data) | M4: 91.666667 | N4: High | O4: Included after full-text eligibility assessment
A5: S04 | B5: 2026 | C5: Engineering Guided Determinism in Neuro-Symbolic Agents: A Comparative Study of Orchestration Strategies for Supply Chain Replenishment | D5: ieee_xplore | E5: 2026 IEEE 50th Annual Computers, Software, and Applications Conference (COMPSAC) | F5: https://ieeexplore.ieee.org/document/11645263/ | G5: Inventory and internal logistics | H5: Inventory management | I5: Hybrid LLM and symbolic or analytical system | J5: Hierarchical or orchestrated | K5: L6 — Full operational autonomy | L5: EM2 — Experimental (simulation / benchmark / synthetic data) | M5: 83.333333 | N5: High | O5: Included after full-text eligibility assessment
A6: S05 | B6: 2026 | C6: Agentic artificial intelligence of things (AIoT) for just-in-time (JIT) logistics and supply chain: a case of modular construction | D6: openalex | E6: International Journal of Logistics Research and Applications | F6: https://openalex.org/W7133835417 | G6: Planning, sourcing, and network design | H6: Supply chain planning | I6: RL-centered multi-agent system | J6: Decentralized | K6: L6 — Full operational autonomy | L6: EM5 — Operational deployment | M6: 95.833333 | N6: High | O6: Included after full-text eligibility assessment
A7: S06 | B7: 2026 | C7: Drivers and constraints of agentic AI in supply chain management: an exploratory study | D7: openalex | E7: International Journal of Production Research | F7: https://openalex.org/W7161700378 | G7: Planning, sourcing, and network design | H7: Supply chain planning | I7: LLM-centered agent system | J7: Conceptual or process-centric | K7: L4 — Supervised execution | L7: EM4 — Real-world pilot or case study | M7: 86.363636 | N7: High | O7: Included after full-text eligibility assessment
A8: S07 | B8: 2026 | C8: “Cognitive Sandwich” architecture for LLM agents in logistics | D8: openalex | E8: Digitalen Hochschulbibliothek Sachsen-Anhalt (Universitäts- und Landesbibliothek Sachsen-Anhalt) | F8: https://openalex.org/W7165113993 | G8: Transportation and distribution | H8: Routing | I8: Hybrid LLM and symbolic or analytical system | J8: Hierarchical or orchestrated | K8: L5 — Conditional autonomy | L8: EM2 — Experimental (simulation / benchmark / synthetic data) | M8: 95.833333 | N8: High | O8: Included after full-text eligibility assessment
A9: S08 | B9: 2026 | C9: Operational Resilience Under Carbon Constraints: A Socio-Technical Multi-Agentic Approach to Global Supply Chains | D9: openalex | E9: Systems | F9: https://openalex.org/W7147895552 | G9: Planning, sourcing, and network design | H9: Supply chain planning | I9: Hybrid LLM and symbolic or analytical system | J9: Hierarchical or orchestrated | K9: L3 — Decision support | L9: EM3 — Real or historical data | M9: 95.833333 | N9: High | O9: Included after full-text eligibility assessment
A10: S09 | B10: 2026 | C10: Automatic Risk-Conscious Hyperconnected Logistics Location Selection via LLM-Based Multi-Agent Systems | D10: openalex | E10: Open MIND | F10: https://openalex.org/W7168649530 | G10: Planning, sourcing, and network design | H10: Location selection | I10: LLM-centered agent system | J10: Hierarchical or orchestrated | K10: L3 — Decision support | L10: EM3 — Real or historical data | M10: 62.5 | N10: Moderate | O10: Included after full-text eligibility assessment
A11: S10 | B11: 2026 | C11: Agentic AI for Demand Forecasting and Planning: Autonomous Market Sensing and Adaptive Planning | D11: openalex | F11: https://openalex.org/W7155182214 | G11: Planning, sourcing, and network design | H11: Supply chain planning | I11: Hybrid LLM and symbolic or analytical system | J11: Hierarchical or orchestrated | K11: L4 — Supervised execution | L11: EM2 — Experimental (simulation / benchmark / synthetic data) | M11: 58.333333 | N11: Moderate | O11: Included after full-text eligibility assessment
A12: S11 | B12: 2026 | C12: Multi-agent deep reinforcement learning for ordering and inventory allocation in a decentralized two-echelon dual-channel supply chain | D12: scopus | E12: International Journal of Production Economics | F12: https://www.scopus.com/inward/record.uri?partnerID=HzOxMe3b&scp=105038448250&origin=inward | G12: Inventory and internal logistics | H12: Inventory management | I12: RL-centered multi-agent system | J12: Decentralized | K12: L5 — Conditional autonomy | L12: EM4 — Real-world data with simulation or benchmarking | M12: 95.833333 | N12: High | O12: Included after full-text eligibility assessment
A13: S12 | B13: 2026 | C13: Structuring the Last Mile with ReActV: Tool-Augmented Delivery Planning with Verification | D13: acm_dl | E13: Companion Publication of the 2026 18th ACM Web Science Conference | F13: https://doi.org/10.1145/3795513.3810458 | G13: Transportation and distribution | H13: Last-mile delivery | I13: LLM-centered agent system | J13: Hierarchical or orchestrated | K13: L3 — Decision support | L13: EM4 — Real-world data with simulation or benchmarking | M13: 95.833333 | N13: High | O13: Included after full-text eligibility assessment
A14: S13 | B14: 2026 | C14: LogiFusion: a semantic-kinetic-dynamic expert system for closed-loop intralogistics decision intelligence | D14: sciencedirect | E14: Expert Systems with Applications | F14: https://www.sciencedirect.com/science/article/pii/S0957417426000618 | G14: Inventory and internal logistics | H14: Intralogistics | I14: Hybrid LLM and symbolic or analytical system | J14: Hierarchical or orchestrated | K14: L4 — Supervised execution | L14: EM2 — Experimental (simulation / benchmark / synthetic data) | M14: 95.833333 | N14: High | O14: Included after full-text eligibility assessment
A15: S14 | B15: 2026 | C15: Towards an Agentic AI-Enabled Blockchain-Based Fish Supply Chain Using Hyperledger Fabric | D15: scopus | E15: Electronics Switzerland | F15: https://www.scopus.com/inward/record.uri?partnerID=HzOxMe3b&scp=105038580626&origin=inward | G15: Operational assurance and asset support | H15: Traceability | I15: Reactive or condition-triggered agent system | J15: Hybrid distributed and governed | K15: L5 — Conditional autonomy | L15: EM1 — Illustrative prototype / proof of concept | M15: 54.166667 | N15: Moderate | O15: Included after full-text eligibility assessment
A16: S15 | B16: 2026 | C16: SCSimulator: An Exploratory Visual Analytics Framework for Partner Selection in Supply Chains through LLM-driven Multi-Agent Simulation | D16: acm_dl | E16: Proceedings of the 31st International Conference on Intelligent User Interfaces | F16: https://doi.org/10.1145/3742413.3789061 | G16: Planning, sourcing, and network design | H16: Partner selection | I16: LLM-centered agent system | J16: Decentralized | K16: L3 — Decision support | L16: EM4 — Real-world data with simulation or benchmarking | M16: 83.333333 | N16: High | O16: Included after full-text eligibility assessment
A17: S16 | B17: 2026 | C17: Leveraging large language models to enhance multi-agent risk assessment in supply chain networks | D17: web_of_science | E17: INTERNATIONAL JOURNAL OF PRODUCTION RESEARCH | F17: https://doi.org/10.1080/00207543.2026.2619562 | G17: Planning, sourcing, and network design | H17: Location selection | I17: LLM-centered agent system | J17: Hierarchical or orchestrated | K17: L3 — Decision support | L17: EM3 — Real or historical data | M17: 95.833333 | N17: High | O17: Included after full-text eligibility assessment
A18: S17 | B18: 2026 | C18: An LLM-empowered collaborative multi-agent framework for intermittent demand forecasting of large-scale spare parts in smart manufacturing | D18: sciencedirect | E18: Knowledge-Based Systems | F18: https://www.sciencedirect.com/science/article/pii/S0950705126010609 | G18: Planning, sourcing, and network design | H18: Demand forecasting | I18: LLM-centered agent system | J18: Hierarchical or orchestrated | K18: L3 — Decision support | L18: EM3 — Real or historical data | M18: 95.833333 | N18: High | O18: Included after full-text eligibility assessment
A19: S18 | B19: 2026 | C19: From text to slot: a multi-agent framework for terminal-oriented container stowage planning via large language models | D19: sciencedirect | E19: Artificial Intelligence for Transportation | F19: https://www.sciencedirect.com/science/article/pii/S3050860626000177 | G19: Transportation and distribution | H19: Stowage planning | I19: LLM-centered agent system | J19: Hierarchical or orchestrated | K19: L5 — Conditional autonomy | L19: EM4 — Real-world data with simulation or benchmarking | M19: 95.833333 | N19: High | O19: Included after full-text eligibility assessment
A20: S19 | B20: 2025 | C20: A Blockchain-Monitored Agentic AI Architecture for Trusted Perception–Reasoning–Action Pipelines | D20: ieee_xplore | E20: 2025 International Conference on Computer and Applications (ICCA) | F20: https://ieeexplore.ieee.org/document/11430865/ | G20: Inventory and internal logistics | H20: Inventory management | I20: LLM-centered agent system | J20: Hierarchical or orchestrated | K20: L5 — Conditional autonomy | L20: EM2 — Experimental (simulation / benchmark / synthetic data) | M20: 91.666667 | N20: High | O20: Included after full-text eligibility assessment
A21: S20 | B21: 2025 | C21: Decentralized pricing in supply chain management: a blockchain-enabled multi-agent Reinforcement Learning approach | D21: ieee_xplore | E21: 2025 11th International Conference on Control, Decision and Information Technologies (CoDIT) | F21: https://ieeexplore.ieee.org/document/11321740/ | G21: Planning, sourcing, and network design | H21: Supply chain planning | I21: RL-centered multi-agent system | J21: Decentralized | K21: L5 — Conditional autonomy | L21: EM2 — Experimental (simulation / benchmark / synthetic data) | M21: 66.666667 | N21: Moderate | O21: Included after full-text eligibility assessment
A22: S21 | B22: 2025 | C22: A Retrieval-Augmented Generation (RAG)-Based LLM for Modern Warehouse Automation and Management | D22: ieee_xplore | E22: 2025 IEEE 21st International Conference on Automation Science and Engineering (CASE) | F22: https://ieeexplore.ieee.org/document/11164106/ | G22: Inventory and internal logistics | H22: Warehousing | I22: LLM-centered agent system | J22: Centralized | K22: L5 — Conditional autonomy | L22: EM2 — Experimental (simulation / benchmark / synthetic data) | M22: 70.833333 | N22: High | O22: Included after full-text eligibility assessment
A23: S22 | B23: 2025 | C23: Leveraging Multi-agent System Powered by Large Language Model to Improve Transparency and Reliability in Automated Supply Chain Coordination | D23: openalex | E23: Annual Conference of the International Group for Lean Construction | F23: https://openalex.org/W4414549039 | G23: Planning, sourcing, and network design | H23: Supply chain planning | I23: LLM-centered agent system | J23: Hierarchical or orchestrated | K23: L5 — Conditional autonomy | L23: EM1 — Illustrative prototype / proof of concept | M23: 66.666667 | N23: Moderate | O23: Included after full-text eligibility assessment
... A31: S30 | B31: 2024 | C31: Optimizing Inventory Management using a Multi-Agent LLM System | D31: scopus | E31: Proceedings of the International Conference on Electronic Business Iceb | F31: https://www.scopus.com/inward/record.uri?partnerID=HzOxMe3b&scp=85213378512&origin=inward | G31: Inventory and internal logistics | H31: Inventory management | I31: LLM-centered agent system | J31: Hierarchical or orchestrated | K31: L5 — Conditional autonomy | L31: EM4 — Real-world data with simulation or benchmarking | M31: 75 | N31: High | O31: Included after full-text eligibility assessment
A32: S31 | B32: 2026 | C32: Generative AI-based optimization for high-mix warehouses: Integrating agentic LLMs and discrete event simulation | D32: sciencedirect | E32: Computers & Industrial Engineering | F32: https://doi.org/10.1016/j.cie.2026.111884 | G32: Inventory and internal logistics | H32: Warehousing | I32: Hybrid LLM and symbolic or analytical system | J32: Centralized | K32: L4 — Supervised execution | L32: EM4 — Real-world data with simulation or benchmarking | M32: ='Quality Assessment'!Q32 -> 91.666667 | N32: ='Quality Assessment'!R32 -> High | O32: Included after full-text eligibility assessment
A33: S32 | B33: 2026 | C33: RationalChain: A Neuro-Symbolic Framework for Explainable Autonomous Negotiation in Supply Chains | D33: ieee_xplore | E33: 2026 10th International Conference on Computing, Communication, Control & Automation (ICCUBEA) | F33: https://doi.org/10.1109/ICCUBEA69821.2026.11702045 | G33: Planning, sourcing, and network design | H33: Purchasing | I33: Hybrid LLM and symbolic or analytical system | J33: Hierarchical or orchestrated | K33: L6 — Full operational autonomy | L33: EM2 — Experimental (simulation / benchmark / synthetic data) | M33: ='Quality Assessment'!Q33 -> 75 | N33: ='Quality Assessment'!R33 -> High | O33: Included after full-text eligibility assessment
A34: S33 | B34: 2026 | C34: Thinking in transit: integrating LLMs and multi-agent systems for agile port-centred container logistics | D34: sciencedirect | E34: Array | F34: https://doi.org/10.1016/j.array.2026.101213 | G34: Transportation and distribution | H34: Transportation | I34: Hybrid LLM and symbolic or analytical system | J34: Hybrid distributed and governed | K34: L5 — Conditional autonomy | L34: EM2 — Experimental (simulation / benchmark / synthetic data) | M34: ='Quality Assessment'!Q34 -> 100 | N34: ='Quality Assessment'!R34 -> High | O34: Included after full-text eligibility assessment
A35: S34 | B35: 2026 | C35: Evolutionary-assisted multi-agent reinforcement learning for waste electrical and electronic equipment inventory optimization under uncertainty | D35: sciencedirect | E35: Engineering Applications of Artificial Intelligence | F35: https://doi.org/10.1016/j.engappai.2026.116478 | G35: Inventory and internal logistics | H35: Inventory management | I35: RL-centered multi-agent system | J35: Decentralized | K35: L5 — Conditional autonomy | L35: EM2 — Experimental (simulation / benchmark / synthetic data) | M35: ='Quality Assessment'!Q35 -> 91.666667 | N35: ='Quality Assessment'!R35 -> High | O35: Included after full-text eligibility assessment
A36: S35 | B36: 2026 | C36: A multi-agent reinforcement learning approach for dynamic supply–demand matching under time variant supply chain topology | D36: sciencedirect | E36: Computers & Industrial Engineering | F36: https://doi.org/10.1016/j.cie.2026.112415 | G36: Planning, sourcing, and network design | H36: Supplier selection | I36: RL-centered multi-agent system | J36: Decentralized | K36: L5 — Conditional autonomy | L36: EM4 — Real-world data with simulation or benchmarking | M36: ='Quality Assessment'!Q36 -> 95.833333 | N36: ='Quality Assessment'!R36 -> High | O36: Included after full-text eligibility assessment
A37: S36 | B37: 2026 | C37: Smart contracts and AI agents for secure last-mile pharmaceutical delivery through crowdsourcing | D37: openalex | E37: Discover Artificial Intelligence | F37: https://openalex.org/W7212254810 | G37: Transportation and distribution | H37: Last-mile delivery | I37: LLM-centered agent system | J37: Hierarchical or orchestrated | K37: L5 — Conditional autonomy | L37: EM4 — Real-world data with simulation or benchmarking | M37: ='Quality Assessment'!Q37 -> 95.833333 | N37: ='Quality Assessment'!R37 -> High | O37: Included after full-text eligibility assessment
A38: S37 | B38: 2026 | C38: A Multi-agent Methodology and Decision-support Toolset for Grain Marketplace Platforms: Coordinating Trade, Transport, and Warehouse Logistics in Agri-food Economic Systems | D38: scopus | E38: International Journal of Intelligent Engineering and Systems | F38: https://www.scopus.com/inward/record.uri?partnerID=HzOxMe3b&scp=105047709702&origin=inward | G38: Planning, sourcing, and network design | H38: Supply chain planning | I38: Mixed intelligent-agent system | J38: Hybrid distributed and governed | K38: L5 — Conditional autonomy | L38: EM3 — Real or historical data | M38: ='Quality Assessment'!Q38 -> 100 | N38: ='Quality Assessment'!R38 -> High | O38: Included after full-text eligibility assessment

Sheet Study Classifications
A1: Study ID | B1: Logistics operations (multi-label) | C1: Agentic paradigms and architectures (multi-label) | D1: Modern agentic capabilities demonstrated | E1: Classical agent capabilities demonstrated | F1: Systems, tools, and data technologies | G1: LLM or base model | H1: Evaluation metrics | I1: Direct baseline
A2: S01 | B2: Inventory management; Freight; Fleet management; Supply chain planning; Routing; Transportation | C2: Intelligent agent; Agentic AI; Decentralized architecture; Multi-agent system | D2: Planning; Replanning; Orchestration | E2: Learning; Communication; Coordination; Perception; Decision-making | F2: knowledge graph/database; LLMs; optimizers; simulation | G2: Not specified | H2: accuracy; cost; robustness and scale; response time; coordination; risk mitigation | I2: Yes
A3: S02 | B3: Warehousing; Purchasing; Distribution; Inventory management; Freight; Supply chain planning; Transportation | C3: Intelligent agent; Agentic AI; Hierarchical architecture; LLM-based agent; Multi-agent system | D3: Tool use; Planning; Memory; Orchestration; Replanning | E3: Communication; Coordination; Perception; Decision-making | F3: APIs; Drools; ERP; Kafka; Kubernetes; Neo4j; Opensearch; Optaplanner; Postgresql; Redis; simulation; Temporal; TMS; WMS | G3: LLM accessed through an API; model not reported; 4,096-token context window | H3: cost; Fill Rate; service level; robustness and scale; response time; Throughput; human acceptance; simulation accuracy | I3: Yes
A4: S03 | B4: Warehousing; Distribution; Inventory management; Fleet management; Supply chain planning; Routing; Transportation | C4: Intelligent agent; Hierarchical architecture; LLM-based agent; Reinforcement-learning agent; Multi-agent system | D4: Tool use; Planning; Replanning; Memory; Orchestration | E4: Task allocation; Learning; Communication; Coordination; Negotiation; Perception; Decision-making | F4: APIs; Digital Twin; Ecp; LLMs; Pytorch; Ray Rllib; simulation; VLA | G4: LLM cluster; DeepSeek and Qwen are mentioned as options, but the deployed model is not identified unambiguously | H4: cost; energy use and emissions; service level; response time; utilization; operational damage; loading/unloading time | I4: Yes
A5: S04 | B5: Purchasing; Inventory management | C5: Agentic AI; Hybrid system; LLM-based agent; Neuro-symbolic system | D5: Tool use; Planning; Orchestration; Reasoning | E5: Perception; Decision-making | F5: Cube; LLMs; Semantic Layer; Text To Sql; symbolic tools | G5: GPT-4.1; temperature 0.1 | H5: execution accuracy; F1; hallucination; latency; Tokens; computational cost; lines of code | I5: Yes
A6: S05 | B6: Warehousing; Modular construction logistics; Inventory management; Fleet management; Supply chain planning; Routing; Transportation | C6: Intelligent agent; Agentic AI; AIoT; BDI/deliberative agent; Decentralized architecture; Reinforcement-learning agent; Multi-agent system | D6: Context awareness; Planning; Replanning; Orchestration; Tool use | E6: Task allocation; Learning; Communication; Coordination; Negotiation; Perception; Decision-making | F6: APIs; Arduino; Dapp; Docker; Fims; Gps Obd; Influxdb; IoT; Kubernetes; Lorawan; Mqtt Grpc; Neo4j; Openai Gym; Pms; RFID/LiDAR; WMS | G6: Not applicable — no LLM used as a central component | H6: Jit Accuracy; autonomous adjustments; inventory cost; recovery time; delivery time; alert effectiveness | I6: Yes
A7: S06 | B7: Warehousing; Purchasing; Distribution; Inventory management; Supply chain planning; Production logistics; Transportation | C7: Intelligent agent; Agentic AI; LLM-based agent | D7: Conceptual discussion only — not counted as demonstrated | E7: Conceptual discussion only — not counted as demonstrated | F7: interviews; company documents; TOE framework; websites | G7: Not applicable — no specific LLM implemented or evaluated | H7: mention frequency; theoretical saturation; participant validation | I7: Not applicable — qualitative exploratory study
A8: S07 | B8: Freight; Supply chain planning; Routing; Transportation | C8: Agentic AI; Hybrid system; LLM-based agent; Neuro-symbolic system | D8: Tool use; Planning; Memory; Orchestration; Reasoning; Replanning | E8: Perception; Decision-making | F8: Arize Phoenix; Fastapi; Highs; Langgraph; MCP; Opentelemetry; Postgresql; Pyomo; Qdrant; Redis; simulation | G8: Gemini 3.1 Flash Lite | H8: task success; response time; Tokens; iterations; revisions; hallucination; recursion | I8: Yes
A9: S08 | B9: Purchasing; Distribution; Inventory management; Freight; Supply chain planning; Routing; Supplier selection; Transportation | C9: Agentic AI; Hierarchical architecture; Hybrid system; LLM-based agent; Multi-agent system | D9: Tool use; Planning; Orchestration; Reasoning | E9: Communication; Coordination; Perception; Decision-making | F9: Aws Bedrock; Boto3; Gradient Boosting; Kmeans; Newsapi; Openrouteservice; Openweathermap; Python; Scikit Learn; Strands Agents; Web Search | G9: Claude 3 Sonnet through AWS Bedrock | H9: accuracy; F1; MAE; Silhouette; cost; carbon emissions; service level; risk; CASP; cross-validation robustness | I9: Partial — comparative models/rules, but no end-to-end baseline for the agentic system
A10: S09 | B10: Supply chain planning; Location selection; Transportation | C10: Hierarchical architecture; LLM-based agent; Multi-agent system | D10: Tool use; Planning; Orchestration; Reasoning | E10: Communication; Coordination; Perception; Decision-making | F10: APIs; public datasets; Fema; Noaa; Epa; Us Accidents | G10: LLM not specified | H10: risk indicators; accidents; pollution; resilience; decision confidence | I10: No
A11: S10 | B11: Purchasing; Inventory management; Supply chain planning | C11: Agentic AI; Hierarchical architecture; Hybrid system; LLM-based agent; Multi-agent system | D11: Context awareness; Planning; Replanning; Orchestration; Reasoning; Tool use | E11: Communication; Coordination; Perception; Decision-making | F11: APIs; Data Lake; ERP; Feature Store; Kafka; LSTM; MIP; Reinforcement Learning; TCN; Transformers | G11: LLM not specified; used for text interpretation, explanations, and communication | H11: forecast error; Overstock; Stockouts | I11: Yes
A12: S11 | B12: Purchasing; Inventory management; Supply chain planning | C12: Decentralized architecture; Reinforcement-learning agent; Multi-agent system | D12: Replanning | E12: Learning; Coordination; Perception; Decision-making | F12: Gumbel Softmax; Optuna; Pytorch; Reinforcement Learning; decision tree; OLS regression; simulation | G12: Not applicable — ChatGPT-4-Turbo and DeepSeek-V3 were used only as baselines | H12: profit; Bullwhip; robustness; scalability; convergence; computational time | I12: Yes
... A38: S37 | B38: Supply chain planning; Purchasing; Transportation; Routing; Warehousing | C38: Intelligent agent; BDI/deliberative agent; Multi-agent system; Decentralized architecture | D38: Planning; Memory; Orchestration; Reasoning; Replanning | E38: Task allocation; Communication; Coordination; Negotiation; Perception; Decision-making | F38: ALNS; APIs; Contract Net Protocol; double auction; fuzzy MCDM; Gurobi; MILP; permissioned ledger; public datasets; simulation | G38: Not applicable — no LLM used | H38: cost; order fulfillment; utilization; allocative efficiency; clearing time; scalability; convergence; emissions; robustness | I38: Yes

Sheet Quality Assessment
A1: Study ID | B1: Year | C1: QA1 | D1: QA2 | E1: QA3 | F1: QA4 | G1: QA5 | H1: QA6 | I1: QA7 | J1: QA8 | K1: QA9 | L1: QA10 | M1: QA11 | N1: QA12 | O1: Score sum | P1: Applicable criteria | Q1: Quality score (%) | R1: Quality class
A2: S01 | B2: 2026 | C2: 1 | D2: 0.5 | E2: 0.5 | F2: 0.5 | G2: 0.5 | H2: 1 | I2: 1 | J2: 0 | K2: 0.5 | L2: 0 | M2: 0.5 | N2: 0.5 | O2: =SUM(C2:N2) -> 6.5 | P2: =COUNT(C2:N2) -> 12 | Q2: =O2/P2*100 -> 54.166667 | R2: =IF(Q2<40,"Low",IF(Q2<70,"Moderate","High")) -> Moderate
A3: S02 | B3: 2026 | C3: 1 | D3: 1 | E3: 1 | F3: 1 | G3: 1 | H3: 1 | I3: 1 | J3: 0.5 | K3: 1 | L3: 1 | M3: 1 | N3: 1 | O3: =SUM(C3:N3) -> 11.5 | P3: =COUNT(C3:N3) -> 12 | Q3: =O3/P3*100 -> 95.833333 | R3: =IF(Q3<40,"Low",IF(Q3<70,"Moderate","High")) -> High
A4: S03 | B4: 2026 | C4: 1 | D4: 1 | E4: 1 | F4: 1 | G4: 1 | H4: 1 | I4: 1 | J4: 0.5 | K4: 1 | L4: 0.5 | M4: 1 | N4: 1 | O4: =SUM(C4:N4) -> 11 | P4: =COUNT(C4:N4) -> 12 | Q4: =O4/P4*100 -> 91.666667 | R4: =IF(Q4<40,"Low",IF(Q4<70,"Moderate","High")) -> High
A5: S04 | B5: 2026 | C5: 1 | D5: 1 | E5: 0.5 | F5: 1 | G5: 1 | H5: 1 | I5: 1 | J5: 0.5 | K5: 1 | L5: 0 | M5: 1 | N5: 1 | O5: =SUM(C5:N5) -> 10 | P5: =COUNT(C5:N5) -> 12 | Q5: =O5/P5*100 -> 83.333333 | R5: =IF(Q5<40,"Low",IF(Q5<70,"Moderate","High")) -> High
A6: S05 | B6: 2026 | C6: 1 | D6: 1 | E6: 1 | F6: 1 | G6: 1 | H6: 1 | I6: 1 | J6: 0.5 | K6: 1 | L6: 1 | M6: 1 | N6: 1 | O6: =SUM(C6:N6) -> 11.5 | P6: =COUNT(C6:N6) -> 12 | Q6: =O6/P6*100 -> 95.833333 | R6: =IF(Q6<40,"Low",IF(Q6<70,"Moderate","High")) -> High
A7: S06 | B7: 2026 | C7: 1 | D7: 0.5 | E7: 1 | F7: 1 | G7: 1 | H7: N/A | I7: 1 | J7: 0.5 | K7: 1 | L7: 1 | M7: 1 | N7: 0.5 | O7: =SUM(C7:N7) -> 9.5 | P7: =COUNT(C7:N7) -> 11 | Q7: =O7/P7*100 -> 86.363636 | R7: =IF(Q7<40,"Low",IF(Q7<70,"Moderate","High")) -> High
A8: S07 | B8: 2026 | C8: 1 | D8: 1 | E8: 1 | F8: 1 | G8: 1 | H8: 1 | I8: 1 | J8: 0.5 | K8: 1 | L8: 1 | M8: 1 | N8: 1 | O8: =SUM(C8:N8) -> 11.5 | P8: =COUNT(C8:N8) -> 12 | Q8: =O8/P8*100 -> 95.833333 | R8: =IF(Q8<40,"Low",IF(Q8<70,"Moderate","High")) -> High
A9: S08 | B9: 2026 | C9: 1 | D9: 1 | E9: 1 | F9: 1 | G9: 1 | H9: 0.5 | I9: 1 | J9: 1 | K9: 1 | L9: 1 | M9: 1 | N9: 1 | O9: =SUM(C9:N9) -> 11.5 | P9: =COUNT(C9:N9) -> 12 | Q9: =O9/P9*100 -> 95.833333 | R9: =IF(Q9<40,"Low",IF(Q9<70,"Moderate","High")) -> High
A10: S09 | B10: 2026 | C10: 1 | D10: 1 | E10: 1 | F10: 0.5 | G10: 0.5 | H10: 0 | I10: 0.5 | J10: 0.5 | K10: 0.5 | L10: 0 | M10: 1 | N10: 1 | O10: =SUM(C10:N10) -> 7.5 | P10: =COUNT(C10:N10) -> 12 | Q10: =O10/P10*100 -> 62.5 | R10: =IF(Q10<40,"Low",IF(Q10<70,"Moderate","High")) -> Moderate
A11: S10 | B11: 2026 | C11: 1 | D11: 1 | E11: 0.5 | F11: 0.5 | G11: 0.5 | H11: 1 | I11: 0.5 | J11: 0 | K11: 0.5 | L11: 0 | M11: 0.5 | N11: 1 | O11: =SUM(C11:N11) -> 7 | P11: =COUNT(C11:N11) -> 12 | Q11: =O11/P11*100 -> 58.333333 | R11: =IF(Q11<40,"Low",IF(Q11<70,"Moderate","High")) -> Moderate
A12: S11 | B12: 2026 | C12: 1 | D12: 1 | E12: 1 | F12: 1 | G12: 1 | H12: 1 | I12: 1 | J12: 0.5 | K12: 1 | L12: 1 | M12: 1 | N12: 1 | O12: =SUM(C12:N12) -> 11.5 | P12: =COUNT(C12:N12) -> 12 | Q12: =O12/P12*100 -> 95.833333 | R12: =IF(Q12<40,"Low",IF(Q12<70,"Moderate","High")) -> High
A13: S12 | B13: 2026 | C13: 1 | D13: 1 | E13: 1 | F13: 1 | G13: 1 | H13: 1 | I13: 1 | J13: 0.5 | K13: 1 | L13: 1 | M13: 1 | N13: 1 | O13: =SUM(C13:N13) -> 11.5 | P13: =COUNT(C13:N13) -> 12 | Q13: =O13/P13*100 -> 95.833333 | R13: =IF(Q13<40,"Low",IF(Q13<70,"Moderate","High")) -> High
A14: S13 | B14: 2026 | C14: 1 | D14: 1 | E14: 1 | F14: 1 | G14: 1 | H14: 1 | I14: 1 | J14: 0.5 | K14: 1 | L14: 1 | M14: 1 | N14: 1 | O14: =SUM(C14:N14) -> 11.5 | P14: =COUNT(C14:N14) -> 12 | Q14: =O14/P14*100 -> 95.833333 | R14: =IF(Q14<40,"Low",IF(Q14<70,"Moderate","High")) -> High
A15: S14 | B15: 2026 | C15: 1 | D15: 0.5 | E15: 0.5 | F15: 0.5 | G15: 0.5 | H15: 0.5 | I15: 0.5 | J15: 0 | K15: 0.5 | L15: 0 | M15: 1 | N15: 1 | O15: =SUM(C15:N15) -> 6.5 | P15: =COUNT(C15:N15) -> 12 | Q15: =O15/P15*100 -> 54.166667 | R15: =IF(Q15<40,"Low",IF(Q15<70,"Moderate","High")) -> Moderate
A16: S15 | B16: 2026 | C16: 1 | D16: 1 | E16: 1 | F16: 1 | G16: 1 | H16: 0.5 | I16: 1 | J16: 0.5 | K16: 0.5 | L16: 0.5 | M16: 1 | N16: 1 | O16: =SUM(C16:N16) -> 10 | P16: =COUNT(C16:N16) -> 12 | Q16: =O16/P16*100 -> 83.333333 | R16: =IF(Q16<40,"Low",IF(Q16<70,"Moderate","High")) -> High
A17: S16 | B17: 2026 | C17: 1 | D17: 1 | E17: 1 | F17: 1 | G17: 1 | H17: 1 | I17: 1 | J17: 0.5 | K17: 1 | L17: 1 | M17: 1 | N17: 1 | O17: =SUM(C17:N17) -> 11.5 | P17: =COUNT(C17:N17) -> 12 | Q17: =O17/P17*100 -> 95.833333 | R17: =IF(Q17<40,"Low",IF(Q17<70,"Moderate","High")) -> High
A18: S17 | B18: 2026 | C18: 1 | D18: 1 | E18: 1 | F18: 1 | G18: 1 | H18: 1 | I18: 1 | J18: 0.5 | K18: 1 | L18: 1 | M18: 1 | N18: 1 | O18: =SUM(C18:N18) -> 11.5 | P18: =COUNT(C18:N18) -> 12 | Q18: =O18/P18*100 -> 95.833333 | R18: =IF(Q18<40,"Low",IF(Q18<70,"Moderate","High")) -> High
A19: S18 | B19: 2026 | C19: 1 | D19: 1 | E19: 1 | F19: 1 | G19: 1 | H19: 1 | I19: 1 | J19: 0.5 | K19: 1 | L19: 1 | M19: 1 | N19: 1 | O19: =SUM(C19:N19) -> 11.5 | P19: =COUNT(C19:N19) -> 12 | Q19: =O19/P19*100 -> 95.833333 | R19: =IF(Q19<40,"Low",IF(Q19<70,"Moderate","High")) -> High
... A38: S37 | B38: 2026 | C38: 1 | D38: 1 | E38: 1 | F38: 1 | G38: 1 | H38: 1 | I38: 1 | J38: 1 | K38: 1 | L38: 1 | M38: 1 | N38: 1 | O38: =SUM(C38:N38) -> 12 | P38: =COUNT(C38:N38) -> 12 | Q38: =O38/P38*100 -> 100 | R38: =IF(Q38<40,"Low",IF(Q38<70,"Moderate","High")) -> High

Sheet QA Criteria
A1: Criterion | B1: Assessment question
A2: QA1 | B2: Are the objectives and logistics problem clearly described?
A3: QA2 | B3: Are the agents, architecture, roles, and interactions specified?
A4: QA3 | B4: Are the claimed capabilities and autonomy demonstrated?
A5: QA4 | B5: Are the data, tools, systems, and evaluation environment described?
A6: QA5 | B6: Is the research/evaluation method appropriate to the objectives?
A7: QA6 | B7: Is there a comparison with a baseline, conventional method, or human process?
A8: QA7 | B8: Are the metrics, results, and analysis presented clearly?
A9: QA8 | B9: Is sufficient detail provided for replication or reproducibility?
A10: QA9 | B10: Is validation performed using simulation, a benchmark, real data, a case study, or a pilot?
A11: QA10 | B11: Are limitations and threats to validity discussed?
A12: QA11 | B12: Are the conclusions supported by the reported results?
... A18: Interpretation | B18: Quality assesses methodological reporting and rigor; it must not be treated as equivalent to evidence maturity.

Sheet Analytical Summary
A1: Dimension | B1: Category | C1: Studies (n) | D1: Share of corpus
A2: Logistics operations | B2: Supply chain planning | C2: 25 | D2: =C2/COUNTA('Primary Studies'!$A$2:$A$38) -> 0.67567568
A3: Logistics operations | B3: Inventory management | C3: 21 | D3: =C3/COUNTA('Primary Studies'!$A$2:$A$38) -> 0.56756757
A4: Logistics operations | B4: Transportation | C4: 21 | D4: =C4/COUNTA('Primary Studies'!$A$2:$A$38) -> 0.56756757
A5: Logistics operations | B5: Routing | C5: 13 | D5: =C5/COUNTA('Primary Studies'!$A$2:$A$38) -> 0.35135135
A6: Logistics operations | B6: Purchasing | C6: 14 | D6: =C6/COUNTA('Primary Studies'!$A$2:$A$38) -> 0.37837838
A7: Logistics operations | B7: Warehousing | C7: 14 | D7: =C7/COUNTA('Primary Studies'!$A$2:$A$38) -> 0.37837838
A8: Paradigms and architectures | B8: Multi-agent systems | C8: 27 | D8: =C8/COUNTA('Primary Studies'!$A$2:$A$38) -> 0.72972973
A9: Paradigms and architectures | B9: LLM-based agents | C9: 25 | D9: =C9/COUNTA('Primary Studies'!$A$2:$A$38) -> 0.67567568
A10: Paradigms and architectures | B10: Explicit agentic AI approaches | C10: 21 | D10: =C10/COUNTA('Primary Studies'!$A$2:$A$38) -> 0.56756757
A11: Paradigms and architectures | B11: Hierarchical architectures | C11: 18 | D11: =C11/COUNTA('Primary Studies'!$A$2:$A$38) -> 0.48648649
A12: Paradigms and architectures | B12: Intelligent-agent approaches | C12: 14 | D12: =C12/COUNTA('Primary Studies'!$A$2:$A$38) -> 0.37837838
A13: Paradigms and architectures | B13: Hybrid systems | C13: 11 | D13: =C13/COUNTA('Primary Studies'!$A$2:$A$38) -> 0.2972973
... A29: Confirmed autonomy | B29: L6 — Full operational autonomy | C29: 5 | D29: =C29/COUNTA('Primary Studies'!$A$2:$A$38) -> 0.13513514
A31: Interpretation note | B31: Percentages for multi-label dimensions do not sum to 100%.
A32: Capability rule | B32: S06 is excluded from demonstrated-capability counts because it reports a conceptual practitioner model rather than an implemented system.
A33: Rounding | B33: Percentages are calculated over the 37-study corpus; trailing decimal zeros are suppressed.
